{
  "success": true,
  "stock_id": "1409",
  "model_type": "lightgbm",
  "best_params": {
    "max_depth": 9,
    "learning_rate": 0.01,
    "n_estimators": 200,
    "subsample": 0.8,
    "colsample_bytree": 1.0
  },
  "best_score": 0.3333333333333333,
  "total_combinations": 10,
  "successful_combinations": 10,
  "failed_combinations": 0,
  "failure_analysis": {},
  "train_period": "2015-01-01 to 2022-12-31",
  "test_period": "2023-01-01 to 2024-12-31",
  "all_results": [
    {
      "combination_id": 1,
      "stock_id": "1409",
      "model_type": "lightgbm",
      "parameters": {
        "max_depth": 9,
        "learning_rate": 0.01,
        "n_estimators": 200,
        "subsample": 0.8,
        "colsample_bytree": 1.0
      },
      "success": true,
      "error_message": null,
      "train_metrics": {
        "mse": 0.008793729442539195,
        "rmse": 0.09377488705692583,
        "mae": 0.07869923921355829,
        "r2": -1.656388186204424,
        "mean_pred": 0.04662706546270102,
        "std_pred": 0.013823583001605163
      },
      "test_score": 0.3333333333333333,
      "test_metrics": {
        "mse": 0.0032543583487357687,
        "rmse": 0.05704698369533458,
        "r2": -1.4383195352095726,
        "direction_accuracy": 0.3333333333333333,
        "mean_pred": 0.03303795274155767,
        "std_pred": 0.015206129400736216
      },
      "feature_count": 72
    },
    {
      "combination_id": 2,
      "stock_id": "1409",
      "model_type": "lightgbm",
      "parameters": {
        "max_depth": 3,
        "learning_rate": 0.1,
        "n_estimators": 50,
        "subsample": 1.0,
        "colsample_bytree": 0.8
      },
      "success": true,
      "error_message": null,
      "train_metrics": {
        "mse": 0.008793729442539196,
        "rmse": 0.09377488705692584,
        "mae": 0.0786992392135583,
        "r2": -1.6563881862044245,
        "mean_pred": 0.04662706546270103,
        "std_pred": 0.013823583001605159
      },
      "test_score": 0.3333333333333333,
      "test_metrics": {
        "mse": 0.0032543583487357687,
        "rmse": 0.05704698369533458,
        "r2": -1.4383195352095726,
        "direction_accuracy": 0.3333333333333333,
        "mean_pred": 0.03303795274155768,
        "std_pred": 0.015206129400736219
      },
      "feature_count": 72
    },
    {
      "combination_id": 3,
      "stock_id": "1409",
      "model_type": "lightgbm",
      "parameters": {
        "max_depth": 3,
        "learning_rate": 0.01,
        "n_estimators": 50,
        "subsample": 1.0,
        "colsample_bytree": 1.0
      },
      "success": true,
      "error_message": null,
      "train_metrics": {
        "mse": 0.008793729442539196,
        "rmse": 0.09377488705692584,
        "mae": 0.07869923921355829,
        "r2": -1.6563881862044245,
        "mean_pred": 0.04662706546270102,
        "std_pred": 0.013823583001605159
      },
      "test_score": 0.3333333333333333,
      "test_metrics": {
        "mse": 0.0032543583487357687,
        "rmse": 0.05704698369533458,
        "r2": -1.4383195352095726,
        "direction_accuracy": 0.3333333333333333,
        "mean_pred": 0.03303795274155767,
        "std_pred": 0.015206129400736219
      },
      "feature_count": 72
    },
    {
      "combination_id": 4,
      "stock_id": "1409",
      "model_type": "lightgbm",
      "parameters": {
        "max_depth": 9,
        "learning_rate": 0.1,
        "n_estimators": 200,
        "subsample": 1.0,
        "colsample_bytree": 0.8
      },
      "success": true,
      "error_message": null,
      "train_metrics": {
        "mse": 0.008793729442539198,
        "rmse": 0.09377488705692584,
        "mae": 0.0786992392135583,
        "r2": -1.6563881862044245,
        "mean_pred": 0.04662706546270102,
        "std_pred": 0.01382358300160516
      },
      "test_score": 0.3333333333333333,
      "test_metrics": {
        "mse": 0.003254358348735768,
        "rmse": 0.05704698369533456,
        "r2": -1.4383195352095717,
        "direction_accuracy": 0.3333333333333333,
        "mean_pred": 0.03303795274155767,
        "std_pred": 0.015206129400736217
      },
      "feature_count": 72
    },
    {
      "combination_id": 5,
      "stock_id": "1409",
      "model_type": "lightgbm",
      "parameters": {
        "max_depth": 3,
        "learning_rate": 0.2,
        "n_estimators": 200,
        "subsample": 1.0,
        "colsample_bytree": 1.0
      },
      "success": true,
      "error_message": null,
      "train_metrics": {
        "mse": 0.008793729442539196,
        "rmse": 0.09377488705692584,
        "mae": 0.07869923921355829,
        "r2": -1.6563881862044245,
        "mean_pred": 0.04662706546270101,
        "std_pred": 0.01382358300160516
      },
      "test_score": 0.3333333333333333,
      "test_metrics": {
        "mse": 0.0032543583487357687,
        "rmse": 0.05704698369533458,
        "r2": -1.4383195352095726,
        "direction_accuracy": 0.3333333333333333,
        "mean_pred": 0.03303795274155767,
        "std_pred": 0.015206129400736219
      },
      "feature_count": 72
    },
    {
      "combination_id": 6,
      "stock_id": "1409",
      "model_type": "lightgbm",
      "parameters": {
        "max_depth": 3,
        "learning_rate": 0.2,
        "n_estimators": 100,
        "subsample": 1.0,
        "colsample_bytree": 1.0
      },
      "success": true,
      "error_message": null,
      "train_metrics": {
        "mse": 0.008793729442539196,
        "rmse": 0.09377488705692584,
        "mae": 0.0786992392135583,
        "r2": -1.6563881862044245,
        "mean_pred": 0.04662706546270102,
        "std_pred": 0.013823583001605159
      },
      "test_score": 0.3333333333333333,
      "test_metrics": {
        "mse": 0.0032543583487357687,
        "rmse": 0.05704698369533458,
        "r2": -1.4383195352095726,
        "direction_accuracy": 0.3333333333333333,
        "mean_pred": 0.03303795274155767,
        "std_pred": 0.015206129400736216
      },
      "feature_count": 72
    },
    {
      "combination_id": 7,
      "stock_id": "1409",
      "model_type": "lightgbm",
      "parameters": {
        "max_depth": 3,
        "learning_rate": 0.2,
        "n_estimators": 100,
        "subsample": 0.8,
        "colsample_bytree": 0.8
      },
      "success": true,
      "error_message": null,
      "train_metrics": {
        "mse": 0.008793729442539196,
        "rmse": 0.09377488705692584,
        "mae": 0.07869923921355829,
        "r2": -1.6563881862044245,
        "mean_pred": 0.04662706546270102,
        "std_pred": 0.013823583001605157
      },
      "test_score": 0.3333333333333333,
      "test_metrics": {
        "mse": 0.0032543583487357687,
        "rmse": 0.05704698369533458,
        "r2": -1.4383195352095726,
        "direction_accuracy": 0.3333333333333333,
        "mean_pred": 0.03303795274155767,
        "std_pred": 0.015206129400736216
      },
      "feature_count": 72
    },
    {
      "combination_id": 8,
      "stock_id": "1409",
      "model_type": "lightgbm",
      "parameters": {
        "max_depth": 3,
        "learning_rate": 0.1,
        "n_estimators": 100,
        "subsample": 0.8,
        "colsample_bytree": 1.0
      },
      "success": true,
      "error_message": null,
      "train_metrics": {
        "mse": 0.008793729442539196,
        "rmse": 0.09377488705692584,
        "mae": 0.07869923921355829,
        "r2": -1.6563881862044245,
        "mean_pred": 0.04662706546270102,
        "std_pred": 0.013823583001605159
      },
      "test_score": 0.3333333333333333,
      "test_metrics": {
        "mse": 0.0032543583487357687,
        "rmse": 0.05704698369533458,
        "r2": -1.4383195352095726,
        "direction_accuracy": 0.3333333333333333,
        "mean_pred": 0.03303795274155767,
        "std_pred": 0.015206129400736217
      },
      "feature_count": 72
    },
    {
      "combination_id": 9,
      "stock_id": "1409",
      "model_type": "lightgbm",
      "parameters": {
        "max_depth": 3,
        "learning_rate": 0.1,
        "n_estimators": 50,
        "subsample": 0.8,
        "colsample_bytree": 1.0
      },
      "success": true,
      "error_message": null,
      "train_metrics": {
        "mse": 0.008793729442539198,
        "rmse": 0.09377488705692584,
        "mae": 0.07869923921355829,
        "r2": -1.6563881862044245,
        "mean_pred": 0.04662706546270102,
        "std_pred": 0.01382358300160516
      },
      "test_score": 0.3333333333333333,
      "test_metrics": {
        "mse": 0.0032543583487357687,
        "rmse": 0.05704698369533458,
        "r2": -1.4383195352095726,
        "direction_accuracy": 0.3333333333333333,
        "mean_pred": 0.03303795274155767,
        "std_pred": 0.015206129400736217
      },
      "feature_count": 72
    },
    {
      "combination_id": 10,
      "stock_id": "1409",
      "model_type": "lightgbm",
      "parameters": {
        "max_depth": 9,
        "learning_rate": 0.1,
        "n_estimators": 50,
        "subsample": 1.0,
        "colsample_bytree": 0.8
      },
      "success": true,
      "error_message": null,
      "train_metrics": {
        "mse": 0.008793729442539195,
        "rmse": 0.09377488705692583,
        "mae": 0.07869923921355831,
        "r2": -1.656388186204424,
        "mean_pred": 0.04662706546270103,
        "std_pred": 0.01382358300160516
      },
      "test_score": 0.3333333333333333,
      "test_metrics": {
        "mse": 0.0032543583487357687,
        "rmse": 0.05704698369533458,
        "r2": -1.4383195352095726,
        "direction_accuracy": 0.3333333333333333,
        "mean_pred": 0.03303795274155768,
        "std_pred": 0.015206129400736219
      },
      "feature_count": 72
    }
  ],
  "created_at": "2025-08-16T11:26:45.796464",
  "results_summary": {
    "top_5_scores": [
      0.3333333333333333,
      0.3333333333333333,
      0.3333333333333333,
      0.3333333333333333,
      0.3333333333333333
    ],
    "mean_score": 0.33333333333333337,
    "std_score": 5.551115123125783e-17
  }
}